claude_worker/__init__.py
claude_worker/cli/__init__.py
claude_worker/cli/config.py
claude_worker/cli/main.py
claude_worker/core/__init__.py
claude_worker/core/database.py
claude_worker/core/error_codes.py
claude_worker/core/executor.py
claude_worker/mcp/__init__.py
claude_worker/mcp/enhanced_proxy.py
claude_worker/mcp/factory.py
claude_worker/mcp/orchestration_tool.py
claude_worker/mcp/proxy.py
claude_worker/mcp/standalone.py
claude_worker/server/__init__.py
claude_worker/server/crud.py
claude_worker/server/database.py
claude_worker/server/error_handler.py
claude_worker/server/executor.py
claude_worker/server/log_formatter.py
claude_worker/server/main.py
claude_worker/server/memory_monitor.py
claude_worker/server/models.py
claude_worker/server/notification.py
claude_worker/server/orchestrator.py
claude_worker/server/path_utils.py
claude_worker/server/retry_handler.py
claude_worker/server/server_logger.py
claude_worker/server/task_logger.py
claude_worker-0.5.0.dist-info/LICENSE
claude_worker-0.5.0.dist-info/METADATA
claude_worker-0.5.0.dist-info/WHEEL
claude_worker-0.5.0.dist-info/entry_points.txt
claude_worker-0.5.0.dist-info/RECORD
