Metadata-Version: 2.3
Name: claude-worker
Version: 0.5.0
Summary: Fire-and-forget task execution system for Claude Code SDK with CLI and MCP interfaces
License: MIT
Keywords: claude,ai,automation,task-queue,cli,mcp,anthropic
Author: Yigit Konur
Author-email: yigit@thinkbuddy.ai
Requires-Python: >=3.10,<4.0
Classifier: Development Status :: 4 - Beta
Classifier: Environment :: Console
Classifier: Framework :: FastAPI
Classifier: Intended Audience :: Developers
Classifier: License :: OSI Approved :: MIT License
Classifier: Operating System :: OS Independent
Classifier: Programming Language :: Python :: 3
Classifier: Programming Language :: Python :: 3.10
Classifier: Programming Language :: Python :: 3.11
Classifier: Programming Language :: Python :: 3.12
Classifier: Programming Language :: Python :: 3.13
Classifier: Topic :: Scientific/Engineering :: Artificial Intelligence
Classifier: Topic :: Software Development :: Libraries :: Python Modules
Provides-Extra: full
Provides-Extra: mcp
Provides-Extra: server
Requires-Dist: claude-code-sdk (>=0.0.19)
Requires-Dist: fastapi (>=0.100.0) ; extra == "server" or extra == "full"
Requires-Dist: fastmcp (>=2.0.0) ; extra == "mcp" or extra == "full"
Requires-Dist: httpx (>=0.25.0) ; extra == "mcp" or extra == "server" or extra == "full"
Requires-Dist: sqlmodel (>=0.0.14)
Requires-Dist: typer[rich] (>=0.12.0) ; extra == "server" or extra == "full"
Requires-Dist: uvicorn[standard] (>=0.23.0) ; extra == "server" or extra == "full"
Project-URL: Bug Tracker, https://github.com/yigitkonur/claude-worker/issues
Project-URL: Changelog, https://github.com/yigitkonur/claude-worker/blob/main/CHANGELOG.md
Project-URL: Documentation, https://github.com/yigitkonur/claude-worker/blob/main/README.md
Project-URL: Homepage, https://github.com/yigitkonur/claude-worker
Project-URL: MCP Documentation, https://github.com/yigitkonur/claude-worker/blob/main/MCP_README.md
Project-URL: Repository, https://github.com/yigitkonur/claude-worker
Project-URL: Smithery, https://smithery.ai/@yigitkonur/claude-worker
